README.rst
setup.cfg
setup.py
src/volworld_common/__init__.py
src/volworld_common.egg-info/PKG-INFO
src/volworld_common.egg-info/SOURCES.txt
src/volworld_common.egg-info/dependency_links.txt
src/volworld_common.egg-info/requires.txt
src/volworld_common.egg-info/top_level.txt
src/volworld_common/api/AuthUser.py
src/volworld_common/api/CA.py
src/volworld_common/api/DefaultBook.py
src/volworld_common/api/DefaultLane.py
src/volworld_common/api/DefaultPuzzle.py
src/volworld_common/api/DefaultSite.py
src/volworld_common/api/NullId.py
src/volworld_common/api/__init__.py
src/volworld_common/api/ca_to_attributes.py
src/volworld_common/api/ca_to_javascript.py
src/volworld_common/api/ca_to_javascript_enum_A.py
src/volworld_common/api/enum/AuthPermission.py
src/volworld_common/api/enum/AuthRole.py
src/volworld_common/api/enum/AuthStatus.py
src/volworld_common/api/enum/CollectTreasureSliceType.py
src/volworld_common/api/enum/ColumnType.py
src/volworld_common/api/enum/CompassRoseType.py
src/volworld_common/api/enum/CompassSphereType.py
src/volworld_common/api/enum/CompassStandType.py
src/volworld_common/api/enum/ErrorCode.py
src/volworld_common/api/enum/HttpStatus.py
src/volworld_common/api/enum/ItemType.py
src/volworld_common/api/enum/LaneDecoratorType.py
src/volworld_common/api/enum/LaneDestinationType.py
src/volworld_common/api/enum/SiteMarkType.py
src/volworld_common/api/enum/SiteStandType.py
src/volworld_common/api/enum/SurfaceType.py
src/volworld_common/api/enum/TrackTerminalType.py
src/volworld_common/api/enum/UserFlagType.py
src/volworld_common/api/enum/UserTitleType.py
src/volworld_common/api/enum/VersionPermissionType.py
src/volworld_common/api/enum/WordBookVersionType.py
src/volworld_common/api/enum/__init__.py
src/volworld_common/api/enum/common_error_code.py
src/volworld_common/test/Timer.py
src/volworld_common/test/__init__.py
src/volworld_common/test/assert_util.py
src/volworld_common/test/dokuwiki.py
src/volworld_common/test/behave/BehaveUtil.py
src/volworld_common/test/behave/ContextUtil.py
src/volworld_common/test/behave/__init__.py
src/volworld_common/util/Base64Utf8.py
src/volworld_common/util/__init__.py
src/volworld_common/util/id_util.py
