Metadata-Version: 2.1
Name: volworld_common
Version: 0.1.94
Home-page: 
Author: Che-Wri, Chang
Author-email: gobidesert.mf@gmail.com
License: MIT
Keywords: volsite
Requires-Dist: aenum
